volmex_python_sdk/__init__.py
volmex_python_sdk/api_client/__init__.py
volmex_python_sdk/api_client/execute.py
volmex_python_sdk/api_client/query.py
volmex_python_sdk/api_client/types/__init__.py
volmex_python_sdk/api_client/types/eip712order.py
volmex_python_sdk/api_client/types/execute.py
volmex_python_sdk/api_client/types/models.py
volmex_python_sdk/api_client/types/query.py
volmex_python_sdk/client/__init__.py
volmex_python_sdk/client/context.py
volmex_python_sdk/contracts/__init__.py
volmex_python_sdk/contracts/abis/AccountBalance.json
volmex_python_sdk/contracts/abis/CollateralManager.json
volmex_python_sdk/contracts/abis/ERC20.json
volmex_python_sdk/contracts/abis/FundingRate.json
volmex_python_sdk/contracts/abis/MatchingEngine.json
volmex_python_sdk/contracts/abis/Periphery.json
volmex_python_sdk/contracts/abis/PerpView.json
volmex_python_sdk/contracts/abis/PerpetualOracle.json
volmex_python_sdk/contracts/abis/Positioning.json
volmex_python_sdk/contracts/abis/PositioningConfig.json
volmex_python_sdk/contracts/abis/QuoteToken.json
volmex_python_sdk/contracts/abis/Vault.json
volmex_python_sdk/contracts/deployments/volmex-chain-testnet/baseTokens.json
volmex_python_sdk/contracts/deployments/volmex-chain-testnet/collateral.json
volmex_python_sdk/contracts/deployments/volmex-chain-testnet/contracts.json
volmex_python_sdk/contracts/deployments/volmex-chain-testnet/urls.json
volmex_python_sdk/contracts/loader.py
volmex_python_sdk/contracts/types.py
volmex_python_sdk/utils/__init__.py
volmex_python_sdk/utils/enum.py
volmex_python_sdk/utils/exceptions.py
volmex_python_sdk/utils/math.py
volmex_python_sdk/utils/model.py
volmex_python_sdk/utils/order.py
volmex_python_sdk/utils/signed_message_to_str.py
volmex_python_sdk/utils/status_codes.py
volmex_python_sdk-0.1.3.dist-info/METADATA
volmex_python_sdk-0.1.3.dist-info/WHEEL
volmex_python_sdk-0.1.3.dist-info/entry_points.txt
volmex_python_sdk-0.1.3.dist-info/RECORD
