Metadata-Version: 2.1
Name: volmex-python-sdk
Version: 0.1.3
Summary: 
Author: jonathan-volmex
Author-email: jonathan@volmexlabs.com
Requires-Python: >=3.9,<4.0
Classifier: Programming Language :: Python :: 3
Classifier: Programming Language :: Python :: 3.9
Classifier: Programming Language :: Python :: 3.10
Classifier: Programming Language :: Python :: 3.11
Classifier: Programming Language :: Python :: 3.12
Requires-Dist: eth-account (>=0.11.0,<0.12.0)
Requires-Dist: pydantic (>=2.7,<3.0)
Requires-Dist: siwe (>=4.1.0,<5.0.0)
Requires-Dist: web3 (>=6.4.0,<7.0.0)
